README.rst
setup.py
mashdown/__init__.py
mashdown/audio.py
mashdown/main.py
mashdown/metadata.py
mashdown/tracklist.py
mashdown.egg-info/PKG-INFO
mashdown.egg-info/SOURCES.txt
mashdown.egg-info/dependency_links.txt
mashdown.egg-info/entry_points.txt
mashdown.egg-info/not-zip-safe
mashdown.egg-info/requires.txt
mashdown.egg-info/top_level.txt
test/test_tracklist.py