Metadata-Version: 1.1
Name: mashdown
Version: 0.1.1
Summary: Download and split a youtube mashup video in a list of tagged audio files
Home-page: UNKNOWN
Author: Balthazar Rouberol
Author-email: brouberol@imap.cc
License: License :: OSI Approved :: MIT License
Platform: UNKNOWN
Classifier: Development Status :: 3 - Alpha
Classifier: Intended Audience :: Developers
Classifier: Natural Language :: English
Classifier: License :: OSI Approved :: MIT License
Classifier: Programming Language :: Python
Classifier: Programming Language :: Python :: 2.6
Classifier: Programming Language :: Python :: 2.7
Classifier: Programming Language :: Python :: 3
Classifier: Programming Language :: Python :: 3.3
Classifier: Programming Language :: Python :: 3.4
Classifier: Topic :: Multimedia :: Sound/Audio :: Conversion
Classifier: Topic :: Multimedia :: Video :: Conversion
